aws_slapdash/__init__.py
aws_slapdash/aws.py
aws_slapdash/cloudformation.py
aws_slapdash/configure.py
aws_slapdash/dynamodb.py
aws_slapdash/ec2.py
aws_slapdash/ecs.py
aws_slapdash/secretsmanager.py
aws_slapdash/utils/__init__.py
aws_slapdash/utils/aws.py
aws_slapdash/utils/command.py
aws_slapdash/utils/slapdash.py
aws_slapdash-0.3.0.dist-info/WHEEL
aws_slapdash-0.3.0.dist-info/METADATA
aws_slapdash-0.3.0.dist-info/RECORD
