Metadata-Version: 2.1
Name: aws-slapdash
Version: 0.3.0
Summary: Slapdash commands for interacting with AWS account
License: GPLv3
Author: glyphack
Author-email: sh.hooshyari@gmail.com
Requires-Python: >=3.8,<4.0
Classifier: License :: Other/Proprietary License
Classifier: Programming Language :: Python :: 3
Classifier: Programming Language :: Python :: 3.8
Classifier: Programming Language :: Python :: 3.9
Classifier: Programming Language :: Python :: 3.10
Classifier: Programming Language :: Python :: 3.11
Requires-Dist: boto3 (>=1.24.89,<2.0.0)
Requires-Dist: boto3-stubs (>=1.24.89,<2.0.0)
